bigbro/__init__.py
bigbro-0.0.1.dist-info/LICENSE
bigbro-0.0.1.dist-info/METADATA
bigbro-0.0.1.dist-info/WHEEL
bigbro-0.0.1.dist-info/top_level.txt
bigbro-0.0.1.dist-info/RECORD
