Metadata-Version: 2.1
Name: bigbro
Version: 0.0.1
Summary: Utilities set for git repositories watching and management
Author-email: Raúl Martín <raul.martin4bc@gmail.com>
License: MIT
Project-URL: Homepage, https://github.com/raul-martin-dev/bigbro
Classifier: Programming Language :: Python :: 3
Classifier: License :: OSI Approved :: MIT License
Classifier: Operating System :: OS Independent
Requires-Python: >=3.7
License-File: LICENSE
